vending_machine.v
module vending_machine(clk,rst,operation);

input clk,rst;
output reg [2:0] operation;
reg [2:0] state;
reg [3:0] counter;
parameter s0 = 0 , s1 = 1 , s2  = 2 , s3 = 3 , s4 = 4 , s5 = 5;
parameter STARTED = 3'b000 , WASHING = 3'b001 , SPINNING = 3'b010 , DRYING = 3'b011 , FINISHED = 3'b100 , HALT = 3'b101;

always @(posedge clk or posedge rst)
begin
if (rst)
state  <= s0;
else
begin
case (state) 

s0 : begin
if (counter < 4'd3)
counter = counter + 1;
else
begin
state <= s1; 
counter <= 0;
end
end

s1 : begin
if (counter < 4'd10)
counter <= counter + 1;
else
begin
state <= s2;
counter <= 0;
end
end

s2 : begin
if (counter < 4'd5)
counter <= counter + 1;
else
begin
state <= s3;
counter <= 0;
end
end

s3 : begin
if (counter < 4'd5)
counter <= counter + 1;
else
begin
state <= s4;
counter <= 0;
end
end

s4 : begin
if (counter < 4'd3)
counter <= counter + 1;
else
begin
state <= s5;
counter <= 0;
end
end

s5 : begin
if (counter < 4'd1)
counter <= counter + 1;
else
begin
state <= s0;
counter <= 0;
end
end
 

default : begin
state <= s0;
counter <= 0;
end
endcase
end
end

always @(posedge clk or posedge rst)
begin
if (rst)
operation <= STARTED;
else
begin
case (state)
s0 : operation <= STARTED;
s1 : operation <= WASHING;
s2 : operation <= SPINNING;
s3 : operation <= DRYING;
s4 : operation <= FINISHED;
s5 : operation <= HALT;
default : operation <= STARTED;
endcase
end
end

endmodule

vending_machine_tb.v
`timescale 100ns/1ps

module vending_machine_tb;

reg clk,rst;
wire [2:0] operation;

vending_machine dut (clk,rst,operation);

always #5 clk = ~clk;

initial
begin
$dumpfile("vending_machine.vcd");
$dumpvars(0,vending_machine_tb);
end

initial 
begin
clk = 0 ; rst = 1;
#7 rst = 0;
#62 rst = 1;
#9 rst = 0;
$display("operations : started(000) washing(001) spinning(010) drying(011) finished(100) halt(101)");
$monitor("time : %g clk : %b rst : %b operation : %b",$time,clk,rst,operation);
#500 $finish;
end
endmodule

vending_machine.vcd
$date
	Tue Jun 17 08:06:58 2025
$end
$version
	Icarus Verilog
$end
$timescale
	1ps
$end
$scope module vending_machine_tb $end
$var wire 3 ! operation [2:0] $end
$var reg 1 " clk $end
$var reg 1 # rst $end
$scope module dut $end
$var wire 1 $ clk $end
$var wire 1 % rst $end
$var reg 4 & counter [3:0] $end
$var reg 3 ' operation [2:0] $end
$var reg 3 ( state [2:0] $end
$upscope $end
$upscope $end
$enddefinitions $end
#0
$dumpvars
b0 (
b0 '
bx &
1%
0$
1#
0"
b0 !
$end
#500000
1"
1$
#700000
0#
0%
#1000000
0"
0$
#1500000
b0 &
b1 (
1"
1$
#2000000
0"
0$
#2500000
b1 '
b1 !
b1 &
1"
1$
#3000000
0"
0$
#3500000
b10 &
1"
1$
#4000000
0"
0$
#4500000
b11 &
1"
1$
#5000000
0"
0$
#5500000
b100 &
1"
1$
#6000000
0"
0$
#6500000
b101 &
1"
1$
#6900000
b0 (
b0 '
b0 !
1#
1%
#7000000
0"
0$
#7500000
1"
1$
#7800000
0#
0%
#8000000
0"
0$
#8500000
b0 &
b1 (
1"
1$
#9000000
0"
0$
#9500000
b1 '
b1 !
b1 &
1"
1$
#10000000
0"
0$
#10500000
b10 &
1"
1$
#11000000
0"
0$
#11500000
b11 &
1"
1$
#12000000
0"
0$
#12500000
b100 &
1"
1$
#13000000
0"
0$
#13500000
b101 &
1"
1$
#14000000
0"
0$
#14500000
b110 &
1"
1$
#15000000
0"
0$
#15500000
b111 &
1"
1$
#16000000
0"
0$
#16500000
b1000 &
1"
1$
#17000000
0"
0$
#17500000
b1001 &
1"
1$
#18000000
0"
0$
#18500000
b1010 &
1"
1$
#19000000
0"
0$
#19500000
b0 &
b10 (
1"
1$
#20000000
0"
0$
#20500000
b1 &
b10 '
b10 !
1"
1$
#21000000
0"
0$
#21500000
b10 &
1"
1$
#22000000
0"
0$
#22500000
b11 &
1"
1$
#23000000
0"
0$
#23500000
b100 &
1"
1$
#24000000
0"
0$
#24500000
b101 &
1"
1$
#25000000
0"
0$
#25500000
b0 &
b11 (
1"
1$
#26000000
0"
0$
#26500000
b1 &
b11 '
b11 !
1"
1$
#27000000
0"
0$
#27500000
b10 &
1"
1$
#28000000
0"
0$
#28500000
b11 &
1"
1$
#29000000
0"
0$
#29500000
b100 &
1"
1$
#30000000
0"
0$
#30500000
b101 &
1"
1$
#31000000
0"
0$
#31500000
b0 &
b100 (
1"
1$
#32000000
0"
0$
#32500000
b1 &
b100 '
b100 !
1"
1$
#33000000
0"
0$
#33500000
b10 &
1"
1$
#34000000
0"
0$
#34500000
b11 &
1"
1$
#35000000
0"
0$
#35500000
b0 &
b101 (
1"
1$
#36000000
0"
0$
#36500000
b1 &
b101 '
b101 !
1"
1$
#37000000
0"
0$
#37500000
b0 &
b0 (
1"
1$
#38000000
0"
0$
#38500000
b0 '
b0 !
b1 &
1"
1$
#39000000
0"
0$
#39500000
b10 &
1"
1$
#40000000
0"
0$
#40500000
b11 &
1"
1$
#41000000
0"
0$
#41500000
b0 &
b1 (
1"
1$
#42000000
0"
0$
#42500000
b1 &
b1 '
b1 !
1"
1$
#43000000
0"
0$
#43500000
b10 &
1"
1$
#44000000
0"
0$
#44500000
b11 &
1"
1$
#45000000
0"
0$
#45500000
b100 &
1"
1$
#46000000
0"
0$
#46500000
b101 &
1"
1$
#47000000
0"
0$
#47500000
b110 &
1"
1$
#48000000
0"
0$
#48500000
b111 &
1"
1$
#49000000
0"
0$
#49500000
b1000 &
1"
1$
#50000000
0"
0$
#50500000
b1001 &
1"
1$
#51000000
0"
0$
#51500000
b1010 &
1"
1$
#52000000
0"
0$
#52500000
b0 &
b10 (
1"
1$
#53000000
0"
0$
#53500000
b10 '
b10 !
b1 &
1"
1$
#54000000
0"
0$
#54500000
b10 &
1"
1$
#55000000
0"
0$
#55500000
b11 &
1"
1$
#56000000
0"
0$
#56500000
b100 &
1"
1$
#57000000
0"
0$
#57500000
b101 &
1"
1$
